tenkan/__init__.py
tenkan/cli.py
tenkan/config.py
tenkan/feed.py
tenkan/feedsfile.py
tenkan/files.py
tenkan/processing.py
tenkan/utils.py
tenkan-0.2.5.dist-info/METADATA
tenkan-0.2.5.dist-info/WHEEL
tenkan-0.2.5.dist-info/entry_points.txt
tenkan-0.2.5.dist-info/RECORD
