Metadata-Version: 2.1
Name: tenkan
Version: 0.2.5
Summary: RSS/atom feed converter from html to gemini
Home-page: https://git.fqserv.eu/takaoni/tenkan
License: WTFPL
Author: Quentin Ferrand
Author-email: quentin.ferrand@protonmail.com
Requires-Python: >=3.8,<4.0
Classifier: License :: Other/Proprietary License
Classifier: Programming Language :: Python :: 3
Classifier: Programming Language :: Python :: 3.8
Classifier: Programming Language :: Python :: 3.9
Classifier: Programming Language :: Python :: 3.10
Classifier: Programming Language :: Python :: 3.11
Requires-Dist: DateTime (>=4.3,<5.0)
Requires-Dist: feedgen (>=0.9.0,<0.10.0)
Requires-Dist: feedparser (>=6.0.8,<7.0.0)
Requires-Dist: markdownify (>=0.10.0,<0.11.0)
Requires-Dist: md2gemini (>=1.8.1,<2.0.0)
Requires-Dist: prettytable (>=3.0.0,<4.0.0)
Requires-Dist: readability-lxml (>=0.8.1,<0.9.0)
Requires-Dist: requests (>=2.26.0,<3.0.0)
Requires-Dist: rich (>=10.16.2,<11.0.0)
Project-URL: Repository, https://git.fqserv.eu/takaoni/tenkan
